pydatamocker/__init__.py
pydatamocker/builder.py
pydatamocker/mock_table.py
pydatamocker/mocker.py
pydatamocker/data/first_name.pkl
pydatamocker/data/last_name.pkl
pydatamocker/util/__init__.py
pydatamocker/util/collections.py
pydatamocker/util/data.py
pydatamocker/util/functions.py
pydatamocker/util/math.py
tests/__init__.py
tests/asserts.py
tests/test_dataset_samples.py
tests/test_datetime_samples.py
tests/test_enum_samples.py
tests/test_mocker.py
tests/test_number_samples.py
tests/tests_util/__init__.py
tests/tests_util/test_math.py
pydatamocker-1.0.0.dist-info/LICENSE
pydatamocker-1.0.0.dist-info/METADATA
pydatamocker-1.0.0.dist-info/WHEEL
pydatamocker-1.0.0.dist-info/top_level.txt
pydatamocker-1.0.0.dist-info/RECORD
