Metadata-Version: 2.1
Name: pydatamocker
Version: 1.0.0
Summary: A data mocker for python scripts and jupyter notebooks
Home-page: https://github.com/msoukharev/pydatamocker
Author: Maxim Soukharev
Author-email: maxim.soukharev@gmail.com
License: UNKNOWN
Project-URL: Bug Tracker, https://github.com/msoukharev/pydatamocker
Platform: UNKNOWN
Classifier: License :: OSI Approved :: MIT License
Classifier: Operating System :: OS Independent
Classifier: Topic :: Software Development :: Testing
Classifier: Topic :: Utilities
Classifier: Programming Language :: Python :: 3
Classifier: Programming Language :: Python :: 3.7
Classifier: Programming Language :: Python :: 3.8
Classifier: Programming Language :: Python :: 3.9
Requires-Python: >=3.7
License-File: LICENSE
